hellojr/__init__.py
hellojr/addition.py
hellojr/addition_tests.py
hellojr/command.py
hellojr/command_tests.py
hellojr/localization.py
hellojr/localization_tests.py
hellojr/multiplcation_tests.py
hellojr/multiplication.py
hellojr/web.py
hellojr/web_tests.py
hellojr-1.0.2.dist-info/LICENSE
hellojr-1.0.2.dist-info/METADATA
hellojr-1.0.2.dist-info/WHEEL
hellojr-1.0.2.dist-info/entry_points.txt
hellojr-1.0.2.dist-info/top_level.txt
hellojr-1.0.2.dist-info/RECORD
